teachmeqmc/BooleanFunction.py
teachmeqmc/Constants.py
teachmeqmc/CoveringMatrix.py
teachmeqmc/LineInQuineMcCluskey.py
teachmeqmc/Utils.py
teachmeqmc/__init__.py
teachmeqmc-0.1.0.dist-info/LICENSE
teachmeqmc-0.1.0.dist-info/METADATA
teachmeqmc-0.1.0.dist-info/WHEEL
teachmeqmc-0.1.0.dist-info/top_level.txt
teachmeqmc-0.1.0.dist-info/RECORD
